[{"index":1,"title":"【回忆】我被天使界主@来的- -","content":"界主说：“让我来给你们讲讲旧嘻吧的故事吧！话说N年前一个叫<a href=\"/i/sys/jump?un=%BE%B2%D2%B9%CB%BC%D1%A9\" onclick=\"Stats.sendRequest('fr=tb0_forum&st_mod=pb&st_value=atlink');\" onmouseover=\"showattip(this)\" onmouseout=\"hideattip(this)\" username=\"%BE%B2%D2%B9%CB%BC%D1%A9\" target=\"_blank\" class=\"at\">@静夜思雪</a> 的家伙来到嘻吧，发表了一篇名为【介绍】嘻哈奇侠传前三集简介的贴子。光阴似箭，日月如梭，现在它已经变成第109页的第46个贴子了。贴子的地址是<a href=\"http://jump2.bdimg.com/safecheck/index?url=x+Z5mMbGPAs95UolpNuq+CwM2BpViN6QmOAUpYcHEp306gWEeMfJBdDJuIuMYa0fg0A84zWu6OUpHbb1muDdYRjsjivx3jduJnH9MnBrW/sZPn6QF1hI9VoW5Kd+yC2eAD9NHM+cr8N6ed5QQwqgsnY9qHh6BM0y\"  target=\"_blank\" rel=\"noopener noreferrer nofollow\"  class=\"j-no-opener-url\" >http://tieba.baidu.com/f?kz=484800909</a>，你可以进去怀旧怀旧。不要挖坟哦！”<br><br>\u0018","author":"静夜思雪","author_link":"https://tieba.baidu.com/home/main?id=tb.1.89f41083.8KjPWz_wRh8PNWU952KLdg&fr=pb","date":"2011-08-23 22:34","ip":null,"old_image":null,"user_sign_image":null},{"index":2,"title":"回复：【回忆】我被天使界主@来的- -","content":"<img class=\"BDE_Smiley\" height=\"40\" src=\"https://gsp0.baidu.com/5aAHeD3nKhI2p27j8IqW0jdnxx1xbK/tb/editor/images/jd/j_0010.gif\" width=\"40\">时光荏苒啊 现在我都要上大学了","author":"静夜思雪","author_link":"https://tieba.baidu.com/home/main?id=tb.1.89f41083.8KjPWz_wRh8PNWU952KLdg&fr=pb","date":"2011-08-23 22:35","ip":null,"old_image":null,"user_sign_image":null},{"index":3,"title":"回复：【回忆】我被天使界主@来的- -","content":"时光荏苒啊，当初我用的就是楼主的头像。","author":"遗失の梦幻","author_link":"https://tieba.baidu.com/home/main?id=tb.1.a99c57e2.HFFB-AtD6zjR9Ho-gTLKgQ&fr=pb","date":"2011-08-24 11:06","ip":null,"old_image":null,"user_sign_image":"https://imgsa.baidu.com/%CB%C0%D2%AFv5/pic/item/3f0e16c6788f5f2ff31fe7d3.jpg?v=tbs"},{"index":5,"title":"回复：【回忆】我被天使界主@来的- -","content":"……准高一路过","author":"激光战斗龙","author_link":"https://tieba.baidu.com/home/main?id=tb.1.87f0cac9.cAfpyxdSnIhCUUbHZdzpKQ?t=1479540062&fr=pb","date":"2011-08-24 12:54","ip":null,"old_image":null,"user_sign_image":null},{"index":6,"title":"回复：【回忆】我被天使界主@来的- -","content":"<img class=\"BDE_Smiley\" height=\"40\" src=\"https://gsp0.baidu.com/5aAHeD3nKhI2p27j8IqW0jdnxx1xbK/tb/editor/images/jd/j_0010.gif\" width=\"40\">我这号头像就一直没换过啊  <br>我这都高中毕业了 嘻哈的大结局居然还是不知道在哪里","author":"静夜思雪","author_link":"https://tieba.baidu.com/home/main?id=tb.1.89f41083.8KjPWz_wRh8PNWU952KLdg&fr=pb","date":"2011-08-24 21:20","ip":null,"old_image":null,"user_sign_image":null},{"index":7,"title":"回复：【回忆】我被天使界主@来的- -","content":"Q Q我还要在初中奋斗……","author":"薇熏香蝶","author_link":"https://tieba.baidu.com/home/main?id=tb.1.7da1cd26.ncgd8hsuEBf2nM6_SvCQRw&fr=pb","date":"2011-08-24 21:58","ip":null,"old_image":null,"user_sign_image":"https://imgsa.baidu.com/forum/pic/item/93ebbbb60a9e4a6727979118.jpg?v=tbs"}]