[{"index":1,"title":"【阿拉】手绘+电脑上色。送我家小玥的图=3=","content":"<img class=\"BDE_Image\" src=\"https://imgsa.baidu.com/forum/w%3D580/sign=2e06ab27510fd9f9a0175561152cd42b/be3785d4b31c8701647536bd277f9e2f0608ff6b.jpg\" width=\"18\" height=\"20\"><br><br>","author":"Twilight_K","author_link":"https://tieba.baidu.com/home/main?id=tb.1.f8af33d5.sKBxFaDIi2iXNcqEYVfgNA&fr=pb","date":"2011-08-25 14:28","ip":null,"old_image":null,"user_sign_image":"https://imgsa.baidu.com/twilight_k/pic/item/2a118becb9a859b2b21cb18e.jpg?v=tbs"},{"index":2,"title":"回复：【阿拉】手绘+电脑上色。送我家小玥的图=3=","content":"= =怎么会那么小<br><img class=\"BDE_Image\" src=\"https://imgsa.baidu.com/forum/w%3D580/sign=ef3766412834349b74066e8df9ea1521/b73b902f07082838d52a5b4fb899a9014c08f10f.jpg\" width=\"336\" height=\"489\"><br><br>","author":"Twilight_K","author_link":"https://tieba.baidu.com/home/main?id=tb.1.f8af33d5.sKBxFaDIi2iXNcqEYVfgNA&fr=pb","date":"2011-08-25 14:30","ip":null,"old_image":null,"user_sign_image":"https://imgsa.baidu.com/76876235/pic/item/2f5bb921e5e8dc6a9922ed3e.jpg?v=tbs?v=tbs"},{"index":3,"title":"回复：【阿拉】手绘+电脑上色。送我家小玥的图=3=","content":"<img class=\"BDE_Smiley\" src=\"https://gsp0.baidu.com/5aAHeD3nKhI2p27j8IqW0jdnxx1xbK/tb/editor/images/jd/j_0006.gif\" width=\"40\" height=\"40\"><br>","author":"我乃嘻哈侠","author_link":"https://tieba.baidu.com/home/main?id=tb.1.29554a22.BBJDljq-FNN7-IqwfwKF7g&fr=pb","date":"2011-08-25 14:54","ip":null,"old_image":null,"user_sign_image":"https://imgsa.baidu.com/%CF%FB%CA%A7%D4%DA%D4%C6%B2%CA%B5%C4%C3%CE/pic/item/384ed1051336f48d7a894717.jpg?v=tbs"},{"index":4,"title":"回复：【阿拉】手绘+电脑上色。送我家小玥的图=3=","content":"各种美好<br>就是不太清楚...<img class=\"BDE_Smiley\" height=\"40\" src=\"https://gsp0.baidu.com/5aAHeD3nKhI2p27j8IqW0jdnxx1xbK/tb/editor/images/jd/j_0013.gif\" width=\"40\">","author":"KING渺","author_link":"https://tieba.baidu.com/home/main?id=tb.1.fb72645f.kn0UEWye8SyHdWRP-ScTew?t=1665701750&fr=pb","date":"2011-08-28 10:06","ip":null,"old_image":null,"user_sign_image":"https://imgsa.baidu.com/kingdawang/pic/item/74ee55a88b8ec4dbca130c2e.jpg?v=tbs"},{"index":5,"title":"回复：【阿拉】手绘+电脑上色。送我家小玥的图=3=","content":"雪爹（妹错／＼） 你AT下笑脸吧","author":"甜蜜de猪猪","author_link":"https://tieba.baidu.com/home/main?id=tb.1.d52ea5a8.DSNW4EcdqgOpaMIQefalnA&fr=pb","date":"2011-08-28 10:07","ip":null,"old_image":null,"user_sign_image":null},{"index":6,"title":"回复：【阿拉】手绘+电脑上色。送我家小玥的图=3=","content":"<img class=\"BDE_Image\" src=\"https://imgsa.baidu.com/forum/w%3D580/sign=87b65c0ff6246b607b0eb27cdbf91a35/2015f6198618367ae30b7d812e738bd4b21ce5b4.jpg\" width=\"570\" height=\"760\" changedsize=\"true\"><br><img class=\"BDE_Smiley\" src=\"https://gsp0.baidu.com/5aAHeD3nKhI2p27j8IqW0jdnxx1xbK/tb/editor/images/jd/j_0039.gif\" width=\"40\" height=\"40\">我送你的在这呢……MUA。<br>\u0018","author":"土萌羊丶丶丶","author_link":"https://tieba.baidu.com/home/main?id=tb.1.aa7d258b.yIV1Crik7rlMsCblUaVOvg?t=1389714112&fr=pb","date":"2011-08-28 15:26","ip":null,"old_image":null,"user_sign_image":"https://imgsa.baidu.com/%CD%C1%C3%C8%D1%F2%D8%BC%D8%BC%D8%BC/pic/item/718211cf3414a77b00e928ff.jpg?v=tbs"}]