[{"index":1,"title":"【寻人】哪位天才教我用PS笔刷刷出动态花瓣...","content":"如题...你得手把手教偶鸟...","author":"尐ル鍠銗°星","author_link":"https://tieba.baidu.com/home/main?id=tb.1.6f22f3bd.zRlzMstlgBTBiov8LWFe3w&fr=pb","date":"2007-04-28 21:55","ip":null,"old_image":null,"user_sign_image":null},{"index":2,"title":"回复：【寻人】哪位天才教我用PS笔刷刷出动态花瓣...","content":"吼!!!!!!!!!!!!!!!!!!!!!!!!!!!!!!!!!!!!!!!!!!!!!!!\r<br>米人理我吗?!!","author":"尐ル鍠銗°星","author_link":"https://tieba.baidu.com/home/main?id=tb.1.6f22f3bd.zRlzMstlgBTBiov8LWFe3w&fr=pb","date":"2007-04-28 22:04","ip":null,"old_image":null,"user_sign_image":null},{"index":3,"title":"回复：【寻人】哪位天才教我用PS笔刷刷出动态花瓣...","content":"ai&nbsp;..........","author":"媚§薰儿","author_link":"https://tieba.baidu.com/home/main?id=tb.1.36df31dc._pjpf6rKMGEW1HH-xJO8RQ&fr=pb","date":"2007-04-28 22:07","ip":null,"old_image":null,"user_sign_image":null}]