[{"index":1,"title":"【格式】闹腾闹腾~~~！！","content":"啊哈哈哈哈~~啊哈哈哈~~~","author":"落璎缥缈","author_link":"https://tieba.baidu.com/home/main?id=tb.1.191c7f61.KviKqzI5P1yW2KXtbuP7Ug&fr=pb","date":"2010-02-04 20:38","ip":null,"old_image":null,"user_sign_image":"https://imgsa.baidu.com/luoyingpiaomiao/pic/item/fd1475fa867b4247034f56b2.jpeg?v=tbs"},{"index":2,"title":"回复：【格式】闹腾闹腾~~~！！","content":"没人陪我闹腾- -","author":"落璎缥缈","author_link":"https://tieba.baidu.com/home/main?id=tb.1.191c7f61.KviKqzI5P1yW2KXtbuP7Ug&fr=pb","date":"2010-02-04 20:39","ip":null,"old_image":null,"user_sign_image":"https://imgsa.baidu.com/luoyingpiaomiao/pic/item/22f76ae609639a1cb8382065.jpg?v=tbs"},{"index":3,"title":"回复：【格式】闹腾闹腾~~~！！","content":"吾就是不会传照片TAT","author":"遗失の梦幻","author_link":"https://tieba.baidu.com/home/main?id=tb.1.a99c57e2.HFFB-AtD6zjR9Ho-gTLKgQ&fr=pb","date":"2010-02-04 20:40","ip":null,"old_image":null,"user_sign_image":"https://imgsa.baidu.com/%D1%A4%D1%A9%B1%F9%D0%C4/pic/item/bf3abdc56caeb2fb39db499d.jpg?v=tbs"},{"index":4,"title":"回复：【格式】闹腾闹腾~~~！！","content":".....[乖","author":"落璎缥缈","author_link":"https://tieba.baidu.com/home/main?id=tb.1.191c7f61.KviKqzI5P1yW2KXtbuP7Ug&fr=pb","date":"2010-02-04 20:42","ip":null,"old_image":null,"user_sign_image":"https://imgsa.baidu.com/luoyingpiaomiao/pic/item/22f76ae609639a1cb8382065.jpg?v=tbs"},{"index":5,"title":"回复：【格式】闹腾闹腾~~~！！","content":"...","author":"遗失の梦幻","author_link":"https://tieba.baidu.com/home/main?id=tb.1.a99c57e2.HFFB-AtD6zjR9Ho-gTLKgQ&fr=pb","date":"2010-02-04 20:42","ip":null,"old_image":null,"user_sign_image":null},{"index":6,"title":"回复：【格式】闹腾闹腾~~~！！","content":"我想看见小云酷睿CD蓝菊猪猪灵嫣。","author":"碎の零潇","author_link":"https://tieba.baidu.com/home/main?id=tb.1.608d7973.xV7eWAOsRC-bHkTaAky9HQ&fr=pb","date":"2010-02-04 20:50","ip":null,"old_image":null,"user_sign_image":null}]