[{"replies":11,"clicks":30,"is_sticky":false,"is_featured":false,"title":"【咿呀】好闲啊啊啊啊啊~~~~~~~","title_link":"?kz=680362173","author":"月_少年","author_link":"https://tieba.baidu.com/home/main?id=tb.1.d529c65b.ayJyCEXSVtAXpFPLcaQg6Q?t=1594050772&fr=pb","last_reply":"12-12","last_reply_by":"遗失の梦幻","last_reply_by_link":"https://tieba.baidu.com/home/main?id=tb.1.a99c57e2.HFFB-AtD6zjR9Ho-gTLKgQ&fr=pb"},{"replies":6,"clicks":19,"is_sticky":false,"is_featured":false,"title":"【求助】我有几道语文题不会,请大家都进来,帮帮忙!谢谢","title_link":"?kz=232012555","author":"220.179.238.*","author_link":null,"last_reply":"12-12","last_reply_by":"110.230.8.*","last_reply_by_link":null},{"replies":4,"clicks":22,"is_sticky":false,"is_featured":false,"title":"【格式】咱们吧的格式消失了？","title_link":"?kz=678049326","author":"许愿星橙","author_link":"https://tieba.baidu.com/home/main?id=tb.1.49c59b21._6Ka7tFRqNAhzTtbGIfv1Q?t=1560654358&fr=pb","last_reply":"12-11","last_reply_by":"许愿星橙","last_reply_by_link":"https://tieba.baidu.com/home/main?id=tb.1.49c59b21._6Ka7tFRqNAhzTtbGIfv1Q?t=1560654358&fr=pb"},{"replies":108,"clicks":456,"is_sticky":false,"is_featured":false,"title":"把你爸,你妈和你名字的最后一个字加起来!读...酷吧!","title_link":"?kz=75900679","author":"淘气xiao丸子","author_link":"https://tieba.baidu.com/home/main?id=tb.1.e8652016.0gyywz7KiiEZNdieFDeRUg&fr=pb","last_reply":"12-10","last_reply_by":"嘻哈粉","last_reply_by_link":"https://tieba.baidu.com/home/main?id=tb.1.401ba93b.Wz6ax4jNnnldw079QnQ1jA&fr=pb"},{"replies":38,"clicks":111,"is_sticky":false,"is_featured":false,"title":"【历史上最强的绕口令】 绕口令高手都来试试! ^ _ ^ 咬到舌头没?","title_link":"?kz=192027264","author":"夜迷茫","author_link":"https://tieba.baidu.com/home/main?id=tb.1.9dd7b6d1.MIb-DJWNvc5dEX4KU_s5FA?t=1472998162&fr=pb","last_reply":"12-6","last_reply_by":"210.21.207.*","last_reply_by_link":null},{"replies":79,"clicks":357,"is_sticky":false,"is_featured":false,"title":"上官帅，GIGI，毛小蒙，葛琪琪你支持哪个？","title_link":"?kz=152760263","author":"61.241.194.*","author_link":null,"last_reply":"12-6","last_reply_by":"嘻哈粉","last_reply_by_link":"https://tieba.baidu.com/home/main?id=tb.1.401ba93b.Wz6ax4jNnnldw079QnQ1jA&fr=pb"},{"replies":781,"clicks":3569,"is_sticky":false,"is_featured":false,"title":"【好玩】你喜欢哪种味道的方便面？（爱情测试）","title_link":"?kz=339416107","author":"落樱寂飘","author_link":"https://tieba.baidu.com/home/main?id=tb.1.65219eaa.SdHWFZO1rDZvk9FH4r6CBA&fr=pb","last_reply":"12-5","last_reply_by":"220.166.62.*","last_reply_by_link":null},{"replies":22,"clicks":56,"is_sticky":false,"is_featured":false,"title":"【呃呃】果然、好多新人- -","title_link":"?kz=674179471","author":"落璎缥缈","author_link":"https://tieba.baidu.com/home/main?id=tb.1.191c7f61.KviKqzI5P1yW2KXtbuP7Ug&fr=pb","last_reply":"12-5","last_reply_by":"121.20.180.*","last_reply_by_link":null},{"replies":5,"clicks":27,"is_sticky":false,"is_featured":false,"title":"【额啊】我忍不住了…………………………………………","title_link":"?kz=661868823","author":"西涼","author_link":"https://tieba.baidu.com/home/main?id=tb.1.b0c95220.OSHr2TA2Qsv4RAKBEW9HOg?t=1539835545&fr=pb","last_reply":"12-4","last_reply_by":"霸气之锋","last_reply_by_link":"https://tieba.baidu.com/home/main?id=tb.1.fffabd74._CS7_M6PazWcFRT9wqs7Ug&fr=pb"},{"replies":1,"clicks":9,"is_sticky":false,"is_featured":false,"title":"【邀请】高桥直纯1206庆生相邀！,","title_link":"?kz=676836757","author":"冰雪叹息","author_link":"https://tieba.baidu.com/home/main?id=tb.1.4b816d13.JK1nb7uUvhGqFFBn7zr5rg&fr=pb","last_reply":"12-3","last_reply_by":"冰雪叹息","last_reply_by_link":"https://tieba.baidu.com/home/main?id=tb.1.4b816d13.JK1nb7uUvhGqFFBn7zr5rg&fr=pb"},{"replies":16,"clicks":70,"is_sticky":false,"is_featured":false,"title":"【天界】教你如何识别验证码","title_link":"?kz=473016574","author":"夭使界主","author_link":"https://tieba.baidu.com/home/main?id=tb.1.53a4a3d9.kerPDAQQx4F4ADvkrS-dVA&fr=pb","last_reply":"12-3","last_reply_by":"newdry","last_reply_by_link":"https://tieba.baidu.com/home/main?id=tb.1.4d6c166.7WLN_mpAKH_Bm7MqbckBmA&fr=pb"},{"replies":1,"clicks":4,"is_sticky":false,"is_featured":false,"title":"【宣传】ALIGIGI吧开张了哦~喜欢GIGI的孩子们要来哦～","title_link":"?kz=675969510","author":"DEVIL逆影","author_link":"https://tieba.baidu.com/home/main?id=tb.1.3d709a8b.JPud94wfM9qKxA-gDCmmhg?t=1492226253&fr=pb","last_reply":"12-1","last_reply_by":"月_少年","last_reply_by_link":"https://tieba.baidu.com/home/main?id=tb.1.d529c65b.ayJyCEXSVtAXpFPLcaQg6Q?t=1594050772&fr=pb"},{"replies":135,"clicks":639,"is_sticky":false,"is_featured":false,"title":"【看吧】你们这群嚣张的女生，看看吧～～绝对比你们PL+LOLI的MM！","title_link":"?kz=473442638","author":"asd425798","author_link":"https://tieba.baidu.com/home/main?id=tb.1.7ba934e.OrAClIFR_SZhZeaiJAqbiQ&fr=pb","last_reply":"11-29","last_reply_by":"119.36.94.*","last_reply_by_link":null},{"replies":0,"clicks":2,"is_sticky":false,"is_featured":false,"title":"【ＸＨ王道－怨念】吧主进！关于吧里的页面整洁！","title_link":"?kz=675179517","author":"DEVIL逆影","author_link":"https://tieba.baidu.com/home/main?id=tb.1.3d709a8b.JPud94wfM9qKxA-gDCmmhg?t=1492226253&fr=pb","last_reply":"11-29","last_reply_by":"DEVIL逆影","last_reply_by_link":"https://tieba.baidu.com/home/main?id=tb.1.3d709a8b.JPud94wfM9qKxA-gDCmmhg?t=1492226253&fr=pb"},{"replies":2,"clicks":14,"is_sticky":false,"is_featured":false,"title":"【ＸＨ王道－原创文】『碎』（嘻哈和死神结合的文哦～）","title_link":"?kz=675155125","author":"DEVIL逆影","author_link":"https://tieba.baidu.com/home/main?id=tb.1.3d709a8b.JPud94wfM9qKxA-gDCmmhg?t=1492226253&fr=pb","last_reply":"11-29","last_reply_by":"DEVIL逆影","last_reply_by_link":"https://tieba.baidu.com/home/main?id=tb.1.3d709a8b.JPud94wfM9qKxA-gDCmmhg?t=1492226253&fr=pb"},{"replies":45,"clicks":121,"is_sticky":false,"is_featured":false,"title":"你会栽在哪种男孩子手里","title_link":"?kz=118528392","author":"浮云残雪泪","author_link":"https://tieba.baidu.com/home/main?id=tb.1.53277d52.MNH2a8Z8_ytAJWilnC8ykg&fr=pb","last_reply":"11-29","last_reply_by":"123.170.140.*","last_reply_by_link":null},{"replies":1,"clicks":6,"is_sticky":false,"is_featured":false,"title":"【呼呼】这次的《嘻哈奇侠传》怎么就3页？","title_link":"?kz=675014349","author":"夜烁银枫雪","author_link":"https://tieba.baidu.com/home/main?id=tb.1.f0267955.oZ7gqIT3mP-TfLFjWJPHww?t=1479696952&fr=pb","last_reply":"11-29","last_reply_by":"清澈无暇的小河","last_reply_by_link":"https://tieba.baidu.com/home/main?id=tb.1.f31dbe7f.EEp2pbrS4aJonE1l8OKYaA&fr=pb"},{"replies":0,"clicks":2,"is_sticky":false,"is_featured":false,"title":"【报道】咱系犽","title_link":"?kz=674994111","author":"Luckittyuan","author_link":"https://tieba.baidu.com/home/main?id=tb.1.49873c50.dnVdDh74xqtRWKGa0IxoLQ&fr=pb","last_reply":"11-29","last_reply_by":"Luckittyuan","last_reply_by_link":"https://tieba.baidu.com/home/main?id=tb.1.49873c50.dnVdDh74xqtRWKGa0IxoLQ&fr=pb"},{"replies":10,"clicks":47,"is_sticky":false,"is_featured":false,"title":"祝福上官帅（上官帅fans必进）","title_link":"?kz=651758006","author":"纯隐伊","author_link":"https://tieba.baidu.com/home/main?id=tb.1.82a3af32.Bp8k40yF8wNH5BuofWiUHA&fr=pb","last_reply":"11-29","last_reply_by":"纯隐伊","last_reply_by_link":"https://tieba.baidu.com/home/main?id=tb.1.82a3af32.Bp8k40yF8wNH5BuofWiUHA&fr=pb"},{"replies":12,"clicks":48,"is_sticky":false,"is_featured":false,"title":"【鼠绘】(╯▽╰)偶尔回来也不知道说毛……仍张垃圾画吧……","title_link":"?kz=674656916","author":"_______莉磨","author_link":"https://tieba.baidu.com/home/main?id=tb.1.4b683bb1.VDcSoubE26m0giqZrbzong&fr=pb","last_reply":"11-29","last_reply_by":"许愿星橙","last_reply_by_link":"https://tieba.baidu.com/home/main?id=tb.1.49c59b21._6Ka7tFRqNAhzTtbGIfv1Q?t=1560654358&fr=pb"},{"replies":7,"clicks":36,"is_sticky":false,"is_featured":false,"title":"【囧囧】是谁又来敲我家门……","title_link":"?kz=674634733","author":"紫·星河","author_link":"https://tieba.baidu.com/home/main?id=tb.1.b5aef5b8.7EHBIRG1L27sAtIpOb0FGA&fr=pb","last_reply":"11-28","last_reply_by":"※云与月※","last_reply_by_link":"https://tieba.baidu.com/home/main?id=tb.1.d2804bbd.Zbxlfx752IqCsbLHdXtmzQ&fr=pb"},{"replies":13,"clicks":68,"is_sticky":false,"is_featured":false,"title":"【爱删不删】我只是来看看老朋友们还在不在的……","title_link":"?kz=671742793","author":"激光战斗龙","author_link":"https://tieba.baidu.com/home/main?id=tb.1.87f0cac9.cAfpyxdSnIhCUUbHZdzpKQ?t=1479540062&fr=pb","last_reply":"11-28","last_reply_by":"月_少年","last_reply_by_link":"https://tieba.baidu.com/home/main?id=tb.1.d529c65b.ayJyCEXSVtAXpFPLcaQg6Q?t=1594050772&fr=pb"},{"replies":6,"clicks":21,"is_sticky":false,"is_featured":false,"title":"【喔哦春哥上新闻三十分了！】【赠春哥日本新消息】","title_link":"?kz=674126092","author":"月_少年","author_link":"https://tieba.baidu.com/home/main?id=tb.1.d529c65b.ayJyCEXSVtAXpFPLcaQg6Q?t=1594050772&fr=pb","last_reply":"11-28","last_reply_by":"※云与月※","last_reply_by_link":"https://tieba.baidu.com/home/main?id=tb.1.d2804bbd.Zbxlfx752IqCsbLHdXtmzQ&fr=pb"},{"replies":64,"clicks":141,"is_sticky":false,"is_featured":false,"title":"【气愤】！！！如果你看了6月号的飒漫画，进下！","title_link":"?kz=587511412","author":"§潇瑶☆曦","author_link":"https://tieba.baidu.com/home/main?id=tb.1.a285844e.eTzxXvhhw1VStGicAR10vQ?t=1463902026&fr=pb","last_reply":"11-28","last_reply_by":"放蕩的年華","last_reply_by_link":"https://tieba.baidu.com/home/main?id=tb.1.1afd9e05.ToDKmmI70ATCkOLPxNCf5g&fr=pb"},{"replies":48,"clicks":161,"is_sticky":false,"is_featured":false,"title":"大家觉得他和上官帅像不像啊~~~(图)","title_link":"?kz=70855729","author":"222.46.101.*","author_link":null,"last_reply":"11-28","last_reply_by":"放蕩的年華","last_reply_by_link":"https://tieba.baidu.com/home/main?id=tb.1.1afd9e05.ToDKmmI70ATCkOLPxNCf5g&fr=pb"},{"replies":20,"clicks":48,"is_sticky":false,"is_featured":false,"title":"【讨论】看来毛小蒙是喜欢葛琪琪的","title_link":"?kz=79249026","author":"帅气小飒","author_link":"https://tieba.baidu.com/home/main?id=tb.1.4c53d729.DgWmPpNuA8yjeTxYQuf9Ag&fr=pb","last_reply":"11-28","last_reply_by":"放蕩的年華","last_reply_by_link":"https://tieba.baidu.com/home/main?id=tb.1.1afd9e05.ToDKmmI70ATCkOLPxNCf5g&fr=pb"},{"replies":28,"clicks":137,"is_sticky":false,"is_featured":false,"title":"【原创】gigi的爱","title_link":"?kz=469961911","author":"BB913","author_link":"https://tieba.baidu.com/home/main?id=tb.1.366b2772.0Rfz9-SQDsFEyW8Y9j7EUg&fr=pb","last_reply":"11-28","last_reply_by":"廖舒舒","last_reply_by_link":"https://tieba.baidu.com/home/main?id=tb.1.25dd4577.Hq0b5pTQ4m146ZrCXl75dw?t=1679646055&fr=pb"},{"replies":4,"clicks":19,"is_sticky":false,"is_featured":false,"title":"【吼】我是上官铎我儿子nei？","title_link":"?kz=650830789","author":"上官铎铎","author_link":"https://tieba.baidu.com/home/main?id=tb.1.311bc6ab.p4BrbZVq-1H_vUvGN_q_nA&fr=pb","last_reply":"11-28","last_reply_by":"221.205.14.*","last_reply_by_link":null},{"replies":51,"clicks":248,"is_sticky":false,"is_featured":false,"title":"【寒心】可怜的狗儿……","title_link":"?kz=534338515","author":"公子·简","author_link":"https://tieba.baidu.com/home/main?id=tb.1.b357b4e3.-rOwRRHCoo_X_dWZ-Jmklw&fr=pb","last_reply":"11-28","last_reply_by":"122.6.133.*","last_reply_by_link":null},{"replies":948,"clicks":1946,"is_sticky":false,"is_featured":false,"title":"【讨论】毛小蒙VS上官帅,谁更帅?","title_link":"?kz=29190239","author":"百度用户#4679429","author_link":"https://tieba.baidu.com/home/main?id=tb.1.b4ea9013.T1K2V8JuXdu3ezHATGNipg?t=1664903897&fr=pb","last_reply":"11-27","last_reply_by":"lhwjs","last_reply_by_link":"https://tieba.baidu.com/home/main?id=tb.1.757df466.K3uxKddtkbmDMukBW6Vprg&fr=pb"},{"replies":42,"clicks":102,"is_sticky":false,"is_featured":false,"title":"【调查】大家都留什么发型？","title_link":"?kz=126435925","author":"o0盖世焘权0o","author_link":"https://tieba.baidu.com/home/main?id=tb.1.cd438b6f.8tlZkAm-6i9tPNlw143XGg&fr=pb","last_reply":"11-27","last_reply_by":"lhwjs","last_reply_by_link":"https://tieba.baidu.com/home/main?id=tb.1.757df466.K3uxKddtkbmDMukBW6Vprg&fr=pb"},{"replies":14,"clicks":68,"is_sticky":false,"is_featured":false,"title":"【囧囧】新人报道","title_link":"?kz=671561261","author":"紫·星河","author_link":"https://tieba.baidu.com/home/main?id=tb.1.b5aef5b8.7EHBIRG1L27sAtIpOb0FGA&fr=pb","last_reply":"11-27","last_reply_by":"mmyy222","last_reply_by_link":"https://tieba.baidu.com/home/main?id=tb.1.7b2fe943.zY-mbkwXa3xf-dDEmcH87w&fr=pb"},{"replies":9,"clicks":48,"is_sticky":false,"is_featured":false,"title":"【玩偶】偶自己画滴，尽管挨鸡蛋砸来吧！","title_link":"?kz=663019757","author":"苹果午餐","author_link":"https://tieba.baidu.com/home/main?id=tb.1.57333c59.voTivJsWv8IDwWQPk1bxXQ&fr=pb","last_reply":"11-27","last_reply_by":"mmyy222","last_reply_by_link":"https://tieba.baidu.com/home/main?id=tb.1.7b2fe943.zY-mbkwXa3xf-dDEmcH87w&fr=pb"},{"replies":24,"clicks":110,"is_sticky":false,"is_featured":false,"title":"【灌水】【天下父母心】三件不能让母亲知道的事！见过也顶一下!","title_link":"?kz=173878273","author":"草莓∮琪琪","author_link":"https://tieba.baidu.com/home/main?id=tb.1.7f8842cf.UOQCjXmO0rb0perQw8oRMw&fr=pb","last_reply":"11-24","last_reply_by":"歌声摇篮","last_reply_by_link":"https://tieba.baidu.com/home/main?id=tb.1.96745c7f.-RYoeM9sxHR1Y1o3ZISr0w&fr=pb"},{"replies":84,"clicks":272,"is_sticky":false,"is_featured":false,"title":"【涂鸦】某星哒烂画阁~HOHO","title_link":"?kz=235691220","author":"尐ル鍠銗°星","author_link":"https://tieba.baidu.com/home/main?id=tb.1.6f22f3bd.zRlzMstlgBTBiov8LWFe3w&fr=pb","last_reply":"11-24","last_reply_by":"124.227.8.*","last_reply_by_link":null},{"replies":3,"clicks":13,"is_sticky":false,"is_featured":false,"title":"【PETER PAN】我觉得幻真的和“毯毯”（王子二世很像）！！","title_link":"?kz=671939777","author":"红鲱鱼の魔术","author_link":"https://tieba.baidu.com/home/main?id=tb.1.204fe5c.5fcxEicQ_wrIzG_hf_3dfQ&fr=pb","last_reply":"11-23","last_reply_by":"jinhongfei41","last_reply_by_link":"https://tieba.baidu.com/home/main?id=tb.1.3ffaf5b8.D9Dss49OQgigXwauMqpkzg&fr=pb"},{"replies":93,"clicks":236,"is_sticky":false,"is_featured":false,"title":"【囧】雪的画-0-~","title_link":"?kz=441885566","author":"飞吟雪","author_link":"https://tieba.baidu.com/home/main?id=tb.1.d50b689b.0t0rQ-kyTg5dC7i7GQS5uA&fr=pb","last_reply":"11-22","last_reply_by":"嗜甜零零","last_reply_by_link":"https://tieba.baidu.com/home/main?id=tb.1.af3baa87.9_fcEuWL7_HvmPXcYbSRBA&fr=pb"},{"replies":5,"clicks":21,"is_sticky":false,"is_featured":false,"title":"【格式】申请会员怎么这么长时间都没有处理?","title_link":"?kz=671813307","author":"夜烁银枫雪","author_link":"https://tieba.baidu.com/home/main?id=tb.1.f0267955.oZ7gqIT3mP-TfLFjWJPHww?t=1479696952&fr=pb","last_reply":"11-22","last_reply_by":"天才魔女见习生","last_reply_by_link":"https://tieba.baidu.com/home/main?id=tb.1.92ea859b.EoaksWuEps0f5v--lTyceQ?t=1404802350&fr=pb"},{"replies":29,"clicks":66,"is_sticky":false,"is_featured":false,"title":"【呐呐】欢迎小梦的归来~","title_link":"?kz=533865497","author":"伊凌雪love帅蒙","author_link":"https://tieba.baidu.com/home/main?id=tb.1.a5ff5a89.HNHZsxoDeyjJbS6DTwthJA&fr=pb","last_reply":"11-22","last_reply_by":"我的鼓囊","last_reply_by_link":"https://tieba.baidu.com/home/main?id=tb.1.f27c8c28.MeVMylLZZLJhafhc1uvUCw&fr=pb"},{"replies":15,"clicks":57,"is_sticky":false,"is_featured":false,"title":"【诗歌】？玫瑰诵【赠玫瑰","title_link":"?kz=585119254","author":"遗失の梦幻","author_link":"https://tieba.baidu.com/home/main?id=tb.1.a99c57e2.HFFB-AtD6zjR9Ho-gTLKgQ&fr=pb","last_reply":"11-21","last_reply_by":"遗失の梦幻","last_reply_by_link":"https://tieba.baidu.com/home/main?id=tb.1.a99c57e2.HFFB-AtD6zjR9Ho-gTLKgQ&fr=pb"},{"replies":6,"clicks":18,"is_sticky":false,"is_featured":false,"title":"【顺便】主人冬瓜你真的死了么、、","title_link":"?kz=671261782","author":"遗失の梦幻","author_link":"https://tieba.baidu.com/home/main?id=tb.1.a99c57e2.HFFB-AtD6zjR9Ho-gTLKgQ&fr=pb","last_reply":"11-21","last_reply_by":"遗失の梦幻","last_reply_by_link":"https://tieba.baidu.com/home/main?id=tb.1.a99c57e2.HFFB-AtD6zjR9Ho-gTLKgQ&fr=pb"},{"replies":16,"clicks":60,"is_sticky":false,"is_featured":false,"title":"【还债】HUHU～！小诗领签了","title_link":"?kz=585035410","author":"千凝☆樱の絮","author_link":"https://tieba.baidu.com/home/main?id=tb.1.d3dee345.ohWd30Km36_mI1o45E2F2A&fr=pb","last_reply":"11-21","last_reply_by":"遗失の梦幻","last_reply_by_link":"https://tieba.baidu.com/home/main?id=tb.1.a99c57e2.HFFB-AtD6zjR9Ho-gTLKgQ&fr=pb"},{"replies":64,"clicks":259,"is_sticky":false,"is_featured":false,"title":"【文章】神之弃子","title_link":"?kz=611823337","author":"书页的故事","author_link":"https://tieba.baidu.com/home/main?id=tb.1.ec15e5e6.2qh4qFSAjSvvbrdjJpO5OA&fr=pb","last_reply":"11-21","last_reply_by":"遗失の梦幻","last_reply_by_link":"https://tieba.baidu.com/home/main?id=tb.1.a99c57e2.HFFB-AtD6zjR9Ho-gTLKgQ&fr=pb"},{"replies":14,"clicks":37,"is_sticky":false,"is_featured":false,"title":"【同好】潜藏了的APH党请来报道~","title_link":"?kz=613778307","author":"Aegean￡爱琴","author_link":"https://tieba.baidu.com/home/main?id=tb.1.124fbc22.7fnctaBDOftkQnk6DDqOMA&fr=pb","last_reply":"11-21","last_reply_by":"落璎缥缈","last_reply_by_link":"https://tieba.baidu.com/home/main?id=tb.1.191c7f61.KviKqzI5P1yW2KXtbuP7Ug&fr=pb"},{"replies":2,"clicks":8,"is_sticky":false,"is_featured":false,"title":"吧里人这么少，大家都干嘛去了啊？！","title_link":"?kz=650039206","author":"纯隐伊","author_link":"https://tieba.baidu.com/home/main?id=tb.1.82a3af32.Bp8k40yF8wNH5BuofWiUHA&fr=pb","last_reply":"11-21","last_reply_by":"落璎缥缈","last_reply_by_link":"https://tieba.baidu.com/home/main?id=tb.1.191c7f61.KviKqzI5P1yW2KXtbuP7Ug&fr=pb"},{"replies":3,"clicks":17,"is_sticky":false,"is_featured":false,"title":"【同人】上官帅一张（无避雷针）","title_link":"?kz=671543194","author":"Oo黑羽青子oO","author_link":"https://tieba.baidu.com/home/main?id=tb.1.a5bda6ce.0Rwt9e5HaybIteATrR-z1Q&fr=pb","last_reply":"11-21","last_reply_by":"隐汐嗳","last_reply_by_link":"https://tieba.baidu.com/home/main?id=tb.1.4b932671.Go2cNh7GTuylSS9ufMFPHw?t=1598233439&fr=pb"},{"replies":7,"clicks":26,"is_sticky":false,"is_featured":false,"title":"【推荐】Happy Tree Friends","title_link":"?kz=528965786","author":"月_少年","author_link":"https://tieba.baidu.com/home/main?id=tb.1.d529c65b.ayJyCEXSVtAXpFPLcaQg6Q?t=1594050772&fr=pb","last_reply":"11-21","last_reply_by":"遗失の梦幻","last_reply_by_link":"https://tieba.baidu.com/home/main?id=tb.1.a99c57e2.HFFB-AtD6zjR9Ho-gTLKgQ&fr=pb"},{"replies":88,"clicks":288,"is_sticky":false,"is_featured":false,"title":"【SARS】飒哥个人资料及漫画赠阅（不断更新中。。。。。）","title_link":"?kz=324330258","author":"亦心绿","author_link":"https://tieba.baidu.com/home/main?id=tb.1.481b88bf.tc8hwiDbg11qsQP7VWuBHw&fr=pb","last_reply":"11-21","last_reply_by":"112.112.132.*","last_reply_by_link":null},{"replies":21,"clicks":62,"is_sticky":false,"is_featured":false,"title":"【小小】要初三了，要上不了了，来点小小的回忆~","title_link":"?kz=636449039","author":"‰墮№天使★","author_link":"https://tieba.baidu.com/home/main?id=tb.1.836d2b6f.Qv142Qxsej6OyR72KjtV2Q&fr=pb","last_reply":"11-21","last_reply_by":"__宫夏°","last_reply_by_link":"https://tieba.baidu.com/home/main?id=tb.1.3724f342.JBgziZBBfEoaKnonx7KTHQ&fr=pb"},{"replies":7,"clicks":22,"is_sticky":false,"is_featured":false,"title":"灵人鱼的眼泪……","title_link":"?kz=105740096","author":"嘉儿之迪路兽","author_link":"https://tieba.baidu.com/home/main?id=tb.1.c8e0e88d.XAX31m8GYrb_xOB7EF1apQ&fr=pb","last_reply":"11-21","last_reply_by":"__宫夏°","last_reply_by_link":"https://tieba.baidu.com/home/main?id=tb.1.3724f342.JBgziZBBfEoaKnonx7KTHQ&fr=pb"}]